colab_jupyter_server/__init__.py
colab_jupyter_server/core.py
colab_jupyter_server-0.8.3.dist-info/METADATA
colab_jupyter_server-0.8.3.dist-info/WHEEL
colab_jupyter_server-0.8.3.dist-info/entry_points.txt
colab_jupyter_server-0.8.3.dist-info/top_level.txt
colab_jupyter_server-0.8.3.dist-info/RECORD
