Metadata-Version: 2.1
Name: colab_jupyter_server
Version: 0.8.3
Summary: Colab/Kaggle as Jupyter a server and kernel
Home-page: https://github.com/alxxtexxr/colab_jupyter_server
Author: alxxtexxr
Author-email: alimtegar404@gmail.com
Classifier: Programming Language :: Python :: 3
Classifier: License :: OSI Approved :: MIT License
Classifier: Operating System :: OS Independent
Requires-Python: >=3.10
Requires-Dist: fire
Requires-Dist: patool
Requires-Dist: requests
Requires-Dist: jupyter-server >=2.14
